ingdavidmurcia_de_toolkit/main.py
ingdavidmurcia_de_toolkit/vm.py
ingdavidmurcia_de_toolkit-0.1.0.dist-info/METADATA
ingdavidmurcia_de_toolkit-0.1.0.dist-info/WHEEL
ingdavidmurcia_de_toolkit-0.1.0.dist-info/entry_points.txt
ingdavidmurcia_de_toolkit-0.1.0.dist-info/RECORD
